lbd/__init__.py
lbd/data/__init__.py
lbd/data/datasets.py
lbd/data/drop.py
lbd/data/transforms.py
lbd/data/utils/__init__.py
lbd/data/utils/dynamic.py
lbd/defense/__init__.py
lbd/defense/base.py
lbd/defense/rnp.py
lbd/model/__init__.py
lbd/model/anp/__init__.py
lbd/model/anp/cifar/__init__.py
lbd/model/anp/in/__init__.py
lbd/model/base/__init__.py
lbd/model/base/in/__init__.py
lbd/model/ftpr/__init__.py
lbd/model/ftpr/cifar/__init__.py
lbd/model/ftpr/cifar/ftpr_conv.py
lbd/model/ftpr/cifar/resnet.py
lbd/model/ftpr/in/__init__.py
lbd/model/rnp/__init__.py
lbd/model/rnp/masked_norm.py
lbd/model/rnp/cifar/__init__.py
lbd/model/rnp/cifar/resnet.py
lbd/model/rnp/in/__init__.py
lbd/util/__init__.py
lbd/util/runtime.py
lib_backdoor-2023.12.1.dist-info/LICENSE
lib_backdoor-2023.12.1.dist-info/METADATA
lib_backdoor-2023.12.1.dist-info/WHEEL
lib_backdoor-2023.12.1.dist-info/dependency_links.txt
lib_backdoor-2023.12.1.dist-info/top_level.txt
lib_backdoor-2023.12.1.dist-info/RECORD
